simplemath4test/__init__.py
simplemath4test/operations.py
simplemath4test-0.1.0.dist-info/LICENSE
simplemath4test-0.1.0.dist-info/METADATA
simplemath4test-0.1.0.dist-info/WHEEL
simplemath4test-0.1.0.dist-info/top_level.txt
simplemath4test-0.1.0.dist-info/RECORD
