Metadata-Version: 2.1
Name: simplemath4test
Version: 0.1.0
Summary: A simple math operations library
Home-page: https://github.com/yourusername/simplemath4test
Author: Your Name
Author-email: your_email@example.com
Classifier: Programming Language :: Python :: 3
Classifier: License :: OSI Approved :: MIT License
Requires-Python: >=3.8
License-File: LICENSE
